{
  "version": "0.63.1",
  "description": "Simple terminal UI for git commands",
  "homepage": "https://github.com/jesseduffield/lazygit",
  "license": "MIT",
  "architecture": {
    "64bit": {
      "url": "https://github.com/jesseduffield/lazygit/releases/download/v0.63.1/lazygit_0.63.1_windows_x86_64.zip",
      "hash": "230721fb5f0d5c0e91555bd4bd76f5213477b116027f1c0fe222b70d49f58ea0"
    },
    "arm64": {
      "url": "https://github.com/jesseduffield/lazygit/releases/download/v0.63.1/lazygit_0.63.1_windows_arm64.zip",
      "hash": "8ced1a9e788cb9b5a8e27f61080ceecede0d76e86fb8ed74d882d2982d480458"
    }
  },
  "bin": [
    [
      "lazygit_0.63.1_windows_x86_64.zip",
      "lazygit"
    ]
  ],
  "autoupdate": {
    "architecture": {
      "64bit": {
        "url": "https://github.com/jesseduffield/lazygit/releases/download/v$version/lazygit_0.63.1_windows_x86_64.zip"
      },
      "arm64": {
        "url": "https://github.com/jesseduffield/lazygit/releases/download/v$version/lazygit_0.63.1_windows_arm64.zip"
      }
    }
  },
  "checkver": {
    "github": "https://github.com/jesseduffield/lazygit"
  }
}
