{
  "version": "sapmachine-25.0.4",
  "description": "SAP's distribution of OpenJDK",
  "homepage": "https://github.com/SAP/SapMachine",
  "license": "GPL-2.0",
  "architecture": {
    "64bit": {
      "url": "https://github.com/SAP/SapMachine/releases/download/sapmachine-25.0.4/sapmachine-jdk-25.0.4_windows-x64_bin.zip",
      "hash": "bf1a4acd32ed09a07946aa110c4ef98a3df6e7f01dde4a12a961af864956c3a2"
    }
  },
  "bin": [
    [
      "sapmachine-jdk-25.0.4_windows-x64_bin.zip",
      "java"
    ]
  ],
  "autoupdate": {
    "architecture": {
      "64bit": {
        "url": "https://github.com/SAP/SapMachine/releases/download/v$version/sapmachine-jdk-25.0.4_windows-x64_bin.zip"
      }
    }
  },
  "checkver": {
    "github": "https://github.com/SAP/SapMachine"
  }
}
